{
    "deangelis": "DeAngelis",
    "deangelo": "DeAngelo",
    "debarge": "DeBarge",
    "deboer": "DeBoer",
    "decarlo": "DeCarlo",
    "dechirico": "DeChirico",
    "decoster": "DeCoster",
    "defalco": "DeFalco",
    "defazio": "DeFazio",
    "defilippo": "DeFilippo",
    "deforest": "DeForest",
    "defrancesco": "DeFrancesco",
    "defranco": "DeFranco",
    "degeneres": "DeGeneres",
    "degroot": "DeGroot",
    "dehaven": "DeHaven",
    "dejesus": "DeJesus",
    "dejong": "DeJong",
    "delacey": "DeLacey",
    "delahoya": "DeLaHoya",
    "delaurentis": "DeLaurentis",
    "delbianco": "DelBianco",
    "delconte": "DelConte",
    "delcorso": "DelCorso",
    "deleon": "DeLeon",
    "deleone": "DeLeone",
    "delgaudio": "DelGaudio",
    "delgreco": "DelGreco",
    "delgrosso": "DelGrosso",
    "delillo": "DeLillo",
    "dell'abate": "Dell'Abate",
    "dell'acqua": "Dell'Acqua",
    "dell'agnese": "Dell'Agnese",
    "dell'anna": "Dell'Anna",
    "dell'anno": "Dell'Anno",
    "dell'olio": "Dell'Olio",
    "dell'orco": "Dell'Orco",
    "dell'orefice": "Dell'Orefice",
    "dell'orto": "Dell'Orto",
    "dell'ova": "Dell'Ova",
    "dell'uomo": "Dell'Uomo",
    "dellacroce": "DellaCroce",
    "dellapenna": "DellaPenna",
    "dellarobbia": "DellaRobbia",
    "dellarusso": "DellaRusso",
    "dellasalla": "DellaSalla",
    "dellavecchia": "DellaVecchia",
    "delmonico": "DelMonico",
    "delonge": "DeLonge",
    "delorean": "DeLorean",
    "delprete": "DelPrete",
    "delsesto": "DelSesto",
    "deluca": "DeLuca",
    "delucia": "DeLucia",
    "deluise": "DeLuise",
    "delvecchio": "DelVecchio",
    "demasi": "DeMasi",
    "demille": "DeMille",
    "demornay": "DeMornay",
    "demoss": "DeMoss",
    "deniro": "DeNiro",
    "depaola": "DePaola",
    "derosa": "DeRosa",
    "derose": "DeRose",
    "desalvo": "DeSalvo",
    "desantis": "DeSantis",
    "desica": "DeSica",
    "desimone": "DeSimone",
    "desoto": "DeSoto",
    "desouza": "DeSouza",
    "destefano": "DeStefano",
    "devane": "DeVane",
    "deville": "DeVille",
    "devito": "DeVito",
    "devos": "DeVos",
    "devries": "DeVries",
    "dewitt": "DeWitt",
    "deyoung": "DeYoung",
    "diagostino": "DiAgostino",
    "diangelo": "DiAngelo",
    "dibella": "DiBella",
    "dibello": "DiBello",
    "dibiase": "DiBiase",
    "dicaprio": "DiCaprio",
    "dicecco": "DiCecco",
    "dicesare": "DiCesare",
    "dicicco": "DiCicco",
    "diclemente": "DiClemente",
    "dicrescenzo": "DiCrescenzo",
    "didario": "DiDario",
    "didonato": "DiDonato",
    "difabio": "DiFabio",
    "difalco": "DiFalco",
    "difelice": "DiFelice",
    "difiore": "DiFiore",
    "difrancesco": "DiFrancesco",
    "digangi": "DiGangi",
    "digennaro": "DiGennaro",
    "digenova": "DiGenova",
    "digeronimo": "DiGeronimo",
    "digiacomo": "DiGiacomo",
    "digiorgio": "DiGiorgio",
    "digiovanni": "DiGiovanni",
    "digiuseppe": "DiGiuseppe",
    "digregorio": "DiGregorio",
    "dilaurentis": "DiLaurentis",
    "dilauro": "DiLauro",
    "dilorenzo": "DiLorenzo",
    "dimaggio": "DiMaggio",
    "dimarco": "DiMarco",
    "dimartino": "DiMartino",
    "dimatteo": "DiMatteo",
    "dimera": "DiMera",
    "dimeo": "DiMeo",
    "dimucci": "DiMucci",
    "dinapoli": "DiNapoli",
    "dinardo": "DiNardo",
    "dinatale": "DiNatale",
    "dinozzo": "DiNozzo",
    "dinunzio": "DiNunzio",
    "dioguardi": "DioGuardi",
    "dipalma": "DiPalma",
    "dipaolo": "DiPaolo",
    "dipasquale": "DiPasquale",
    "dipietro": "DiPietro",
    "dipinto": "DiPinto",
    "diprima": "DiPrima",
    "dirienzo": "DiRienzo",
    "dirocco": "DiRocco",
    "disalvo": "DiSalvo",
    "disanto": "DiSanto",
    "discala": "DiScala",
    "dispirito": "DiSpirito",
    "distefano": "DiStefano",
    "ditommaso": "DiTommaso",
    "divincenzo": "DiVincenzo",
    "dubois": "DuBois",
    "dumonde": "DuMonde",
    "dupont": "DuPont",
    "duvernay": "DuVernay",
    "labarbera": "LaBarbera",
    "labelle": "LaBelle",
    "labianca": "LaBianca",
    "lacamera": "LaCamera",
    "lachapelle": "LaChapelle",
    "lacroix": "LaCroix",
    "lafave": "LaFave",
    "lafollette": "LaFollette",
    "lafontaine": "LaFontaine",
    "laforge": "LaForge",
    "lagravenese": "LaGravenese",
    "laguardia": "LaGuardia",
    "laloggia": "LaLoggia",
    "lamotta": "LaMotta",
    "lapaglia": "LaPaglia",
    "lapierre": "LaPierre",
    "laplante": "LaPlante",
    "larocca": "LaRocca",
    "larocque": "LaRocque",
    "larussa": "LaRussa",
    "lasalle": "LaSalle",
    "lebeau": "LeBeau",
    "leblanc": "LeBlanc",
    "lebron": "LeBron",
    "lecroy": "LeCroy",
    "leflore": "LeFlore",
    "lemieux": "LeMieux",
    "lemond": "LeMond"
}
